README.rst
setup.cfg
setup.py
gimme_input/__init__.py
gimme_input/bool_user_input.py
gimme_input/input_grabbers.py
gimme_input/resolvable.py
gimme_input/user_choice.py
gimme_input/user_input.py
gimme_input/user_input_error.py
gimme_input/user_multi_choice.py
gimme_input.egg-info/PKG-INFO
gimme_input.egg-info/SOURCES.txt
gimme_input.egg-info/dependency_links.txt
gimme_input.egg-info/top_level.txt
tests/__init__.py
tests/test_sample.py