Metadata-Version: 1.1
Name: gimme-input
Version: 1.0.0
Summary: A library of useful functions to get input from users for command line programs.
Home-page: https://github.com/dcdanko/gimme_input
Author: David C. Danko
Author-email: dcdanko@gmail.com
License: UNKNOWN
Platform: UNKNOWN
Classifier: Development Status :: 2 - Pre-Alpha
Classifier: Programming Language :: Python
Classifier: Programming Language :: Python :: 3
Classifier: Programming Language :: Python :: 3.4
Classifier: Programming Language :: Python :: 3.5
